[
  {
    "examId": 1,
    "examDate": "Oct 1, 44895395 11:16:27 AM",
    "answeredQuestions": [
      {
        "questionId": 1,
        "resultWasGood": true,
        "questionText": "Vraag nummer 1 over ATAM",
        "categories": [
          "ATAM"
        ],
        "questionType": "OpenQuestion",
        "answerType": "MultipleChoiceQuestion",
        "answeredOn": "Oct 1, 44895395 11:16:27 AM"
      },
      {
        "questionId": 32,
        "resultWasGood": false,
        "questionText": "Vraag nummer 32 over DCAR",
        "categories": [
          "DCAR"
        ],
        "questionType": "OpenQuestion",
        "answerType": "MultipleChoiceQuestion",
        "answeredOn": "Feb 4, 129060974 7:55:57 AM"
      },
      {
        "questionId": 2,
        "resultWasGood": false,
        "questionText": "Vraag nummer 2 over QA",
        "categories": [
          "QA"
        ],
        "questionType": "OpenQuestion",
        "answerType": "MultipleChoiceQuestion",
        "answeredOn": "Oct 1, 44895395 11:16:27 AM"
      },
      {
        "questionId": 3,
        "resultWasGood": false,
        "questionText": "Vraag nummer 3 over ASR",
        "categories": [
          "ASR"
        ],
        "questionType": "OpenQuestion",
        "answerType": "MultipleChoiceQuestion",
        "answeredOn": "Oct 1, 44895395 11:16:27 AM"
      },
      {
        "questionId": 4,
        "resultWasGood": true,
        "questionText": "Vraag nummer 4 over DCAR",
        "categories": [
          "DCAR"
        ],
        "questionType": "OpenQuestion",
        "answerType": "MultipleChoiceQuestion",
        "answeredOn": "Oct 1, 44895395 11:16:27 AM"
      },
      {
        "questionId": 5,
        "resultWasGood": true,
        "questionText": "Vraag nummer 5 over ATAM",
        "categories": [
          "ATAM"
        ],
        "questionType": "multipleChoice",
        "answerType": "MultipleChoiceQuestion",
        "answeredOn": "Oct 1, 44895395 11:16:27 AM"
      },
      {
        "questionId": 6,
        "resultWasGood": false,
        "questionText": "Vraag nummer 6 over QA",
        "categories": [
          "QA"
        ],
        "questionType": "OpenQuestion",
        "answerType": "MultipleChoiceQuestion",
        "answeredOn": "Oct 1, 44895395 11:16:27 AM"
      },
      {
        "questionId": 7,
        "resultWasGood": false,
        "questionText": "Vraag nummer 7 over ASR",
        "categories": [
          "ASR",
          "QA",
          "AVL"
        ],
        "questionType": "OpenQuestion",
        "answerType": "MultipleChoiceQuestion",
        "answeredOn": "Oct 1, 44895395 11:16:27 AM"
      },
      {
        "questionId": 8,
        "resultWasGood": true,
        "questionText": "Vraag nummer 8 over DCAR",
        "categories": [
          "DCAR"
        ],
        "questionType": "OpenQuestion",
        "answerType": "MultipleChoiceQuestion",
        "answeredOn": "Oct 1, 44895395 11:16:27 AM"
      }
    ]
  },
  {
    "examId": 2,
    "examDate": "Aug 13, 108302150 7:41:18 AM",
    "answeredQuestions": [
      {
        "questionId": 9,
        "resultWasGood": false,
        "questionText": "Vraag nummer 9 over ATAM",
        "categories": [
          "ATAM"
        ],
        "questionType": "OpenQuestion",
        "answerType": "MultipleChoiceQuestion",
        "answeredOn": "Aug 13, 108302150 7:41:18 AM"
      },
      {
        "questionId": 10,
        "resultWasGood": true,
        "questionText": "Vraag nummer 10 over QA",
        "categories": [
          "QA"
        ],
        "questionType": "OpenQuestion",
        "answerType": "MultipleChoiceQuestion",
        "answeredOn": "Aug 13, 108302150 7:41:18 AM"
      },
      {
        "questionId": 11,
        "resultWasGood": false,
        "questionText": "Vraag nummer 11 over ASR",
        "categories": [
          "ASR"
        ],
        "questionType": "OpenQuestion",
        "answerType": "MultipleChoiceQuestion",
        "answeredOn": "Aug 13, 108302150 7:41:18 AM"
      },
      {
        "questionId": 12,
        "resultWasGood": true,
        "questionText": "Vraag nummer 12 over DCAR",
        "categories": [
          "DCAR",
          "ASR"
        ],
        "questionType": "OpenQuestion",
        "answerType": "MultipleChoiceQuestion",
        "answeredOn": "Aug 13, 108302150 7:41:18 AM"
      },
      {
        "questionId": 13,
        "resultWasGood": true,
        "questionText": "Vraag nummer 13 over ATAM",
        "categories": [
          "ATAM"
        ],
        "questionType": "OpenQuestion",
        "answerType": "MultipleChoiceQuestion",
        "answeredOn": "Aug 13, 108302150 7:41:18 AM"
      },
      {
        "questionId": 14,
        "resultWasGood": false,
        "questionText": "Vraag nummer 14 over QA",
        "categories": [
          "QA"
        ],
        "questionType": "OpenQuestion",
        "answerType": "MultipleChoiceQuestion",
        "answeredOn": "Aug 13, 108302150 7:41:18 AM"
      },
      {
        "questionId": 15,
        "resultWasGood": true,
        "questionText": "Vraag nummer 15 over ASR",
        "categories": [
          "ASR"
        ],
        "questionType": "OpenQuestion",
        "answerType": "MultipleChoiceQuestion",
        "answeredOn": "Aug 13, 108302150 7:41:18 AM"
      },
      {
        "questionId": 16,
        "resultWasGood": true,
        "questionText": "Vraag nummer 16 over DCAR",
        "categories": [
          "DCAR"
        ],
        "questionType": "multipleChoice",
        "answerType": "MultipleChoiceQuestion",
        "answeredOn": "Aug 13, 108302150 7:41:18 AM"
      }
    ]
  },
  {
    "examId": 3,
    "examDate": "Mar 24, 65030890 9:15:14 PM",
    "answeredQuestions": [
      {
        "questionId": 17,
        "resultWasGood": false,
        "questionText": "Vraag nummer 17 over ATAM",
        "categories": [
          "ATAM",
          "DCAR"
        ],
        "questionType": "OpenQuestion",
        "answerType": "MultipleChoiceQuestion",
        "answeredOn": "Mar 24, 65030890 9:15:14 PM"
      },
      {
        "questionId": 18,
        "resultWasGood": false,
        "questionText": "Vraag nummer 18 over QA",
        "categories": [
          "QA"
        ],
        "questionType": "OpenQuestion",
        "answerType": "MultipleChoiceQuestion",
        "answeredOn": "Mar 24, 65030890 9:15:14 PM"
      },
      {
        "questionId": 19,
        "resultWasGood": true,
        "questionText": "Vraag nummer 19 over ASR",
        "categories": [
          "ASR"
        ],
        "questionType": "OpenQuestion",
        "answerType": "MultipleChoiceQuestion",
        "answeredOn": "Mar 24, 65030890 9:15:14 PM"
      },
      {
        "questionId": 20,
        "resultWasGood": false,
        "questionText": "Vraag nummer 20 over DCAR",
        "categories": [
          "DCAR"
        ],
        "questionType": "OpenQuestion",
        "answerType": "MultipleChoiceQuestion",
        "answeredOn": "Mar 24, 65030890 9:15:14 PM"
      },
      {
        "questionId": 21,
        "resultWasGood": false,
        "questionText": "Vraag nummer 21 over ATAM",
        "categories": [
          "ATAM"
        ],
        "questionType": "OpenQuestion",
        "answerType": "MultipleChoiceQuestion",
        "answeredOn": "Mar 24, 65030890 9:15:14 PM"
      },
      {
        "questionId": 22,
        "resultWasGood": true,
        "questionText": "Vraag nummer 22 over QA",
        "categories": [
          "QA"
        ],
        "questionType": "OpenQuestion",
        "answerType": "MultipleChoiceQuestion",
        "answeredOn": "Mar 24, 65030890 9:15:14 PM"
      },
      {
        "questionId": 23,
        "resultWasGood": false,
        "questionText": "Vraag nummer 23 over ASR",
        "categories": [
          "ASR"
        ],
        "questionType": "OpenQuestion",
        "answerType": "MultipleChoiceQuestion",
        "answeredOn": "Mar 24, 65030890 9:15:14 PM"
      },
      {
        "questionId": 24,
        "resultWasGood": true,
        "questionText": "Vraag nummer 24 over DCAR",
        "categories": [
          "DCAR"
        ],
        "questionType": "OpenQuestion",
        "answerType": "MultipleChoiceQuestion",
        "answeredOn": "Mar 24, 65030890 9:15:14 PM"
      }
    ]
  },
  {
    "examId": 4,
    "examDate": "Feb 4, 129060974 7:55:57 AM",
    "answeredQuestions": [
      {
        "questionId": 25,
        "resultWasGood": false,
        "questionText": "Vraag nummer 25 over ATAM",
        "categories": [
          "ATAM"
        ],
        "questionType": "OpenQuestion",
        "answerType": "MultipleChoiceQuestion",
        "answeredOn": "Feb 4, 129060974 7:55:57 AM"
      },
      {
        "questionId": 26,
        "resultWasGood": true,
        "questionText": "Vraag nummer 26 over QA",
        "categories": [
          "QA"
        ],
        "questionType": "OpenQuestion",
        "answerType": "MultipleChoiceQuestion",
        "answeredOn": "Feb 4, 129060974 7:55:57 AM"
      },
      {
        "questionId": 27,
        "resultWasGood": false,
        "questionText": "Vraag nummer 27 over ASR",
        "categories": [
          "ASR"
        ],
        "questionType": "multipleChoice",
        "answerType": "MultipleChoiceQuestion",
        "answeredOn": "Feb 4, 129060974 7:55:57 AM"
      },
      {
        "questionId": 28,
        "resultWasGood": false,
        "questionText": "Vraag nummer 28 over DCAR",
        "categories": [
          "DCAR"
        ],
        "questionType": "OpenQuestion",
        "answerType": "MultipleChoiceQuestion",
        "answeredOn": "Feb 4, 129060974 7:55:57 AM"
      },
      {
        "questionId": 29,
        "resultWasGood": false,
        "questionText": "Vraag nummer 29 over ATAM",
        "categories": [
          "ATAM"
        ],
        "questionType": "OpenQuestion",
        "answerType": "MultipleChoiceQuestion",
        "answeredOn": "Feb 4, 129060974 7:55:57 AM"
      },
      {
        "questionId": 30,
        "resultWasGood": true,
        "questionText": "Vraag nummer 30 over QA",
        "categories": [
          "QA"
        ],
        "questionType": "OpenQuestion",
        "answerType": "MultipleChoiceQuestion",
        "answeredOn": "Feb 4, 129060974 7:55:57 AM"
      },
      {
        "questionId": 31,
        "resultWasGood": false,
        "questionText": "Vraag nummer 31 over ASR",
        "categories": [
          "ASR"
        ],
        "questionType": "OpenQuestion",
        "answerType": "MultipleChoiceQuestion",
        "answeredOn": "Feb 4, 129060974 7:55:57 AM"
      },
      {
        "questionId": 32,
        "resultWasGood": false,
        "questionText": "Vraag nummer 32 over DCAR",
        "categories": [
          "DCAR"
        ],
        "questionType": "OpenQuestion",
        "answerType": "MultipleChoiceQuestion",
        "answeredOn": "Feb 4, 129060974 7:55:57 AM"
      }
    ]
  }
]