[
  {
    "questionId": 7,
    "resultWasGood": false,
    "questionText": "Vraag nummer 7 over ASR",
    "categories": [
      "ASR",
      "QA"
    ],
    "type": "OpenQuestion"
  },
  {
    "questionId": 20,
    "resultWasGood": false,
    "questionText": "Beantwoorde vraag over ASR",
    "categories": [
      "DCAR"
    ],
    "type": "OpenQuestion",
    "answeredOn": "2018-01-03T14:39:14.534Z"
  },
  {
    "questionId": 21,
    "resultWasGood": true,
    "questionText": "Beantwoorde vraag over ASR",
    "categories": [
      "ATAM"
    ],
    "type": "OpenQuestion",
    "answeredOn": "2018-05-03T14:39:14.534Z"
  },
  {
    "questionId": 22,
    "resultWasGood": false,
    "questionText": "Beantwoorde vraag over DCAR",
    "categories": [
      "QA"
    ],
    "type": "OpenQuestion",
    "answeredOn": "2018-06-03T14:39:14.534Z"
  },
  {
    "questionId": 23,
    "resultWasGood": true,
    "questionText": "Beantwoorde vraag over DCAR",
    "categories": [
      "ASR"
    ],
    "type": "OpenQuestion",
    "answeredOn": "2018-02-03T14:39:14.534Z"
  },
  {
    "questionId": 24,
    "resultWasGood": true,
    "questionText": "Beantwoorde vraag over ATAM",
    "categories": [
      "DCAR"
    ],
    "type": "OpenQuestion",
    "answeredOn": "2018-07-03T14:39:14.534Z"
  },
  {
    "questionId": 25,
    "resultWasGood": false,
    "questionText": "Beantwoorde vraag over ATAM",
    "categories": [
      "ATAM"
    ],
    "type": "OpenQuestion",
    "answeredOn": "2018-06-03T14:39:14.534Z"
  },
  {
    "questionId": 26,
    "resultWasGood": true,
    "questionText": "Beantwoorde vraag over QA",
    "categories": [
      "QA"
    ],
    "type": "OpenQuestion",
    "answeredOn": "2018-06-03T14:39:14.534Z"
  },
  {
    "questionId": 27,
    "resultWasGood": false,
    "questionText": "Beantwoorde vraag over QA",
    "categories": [
      "ASR"
    ],
    "type": "OpenQuestion",
    "answeredOn": "2018-03-03T14:39:14.534Z"
  }
]